GOBC_PA/GOBC_PA.py
GOBC_PA/__init__.py
gobc_pa-1.3.dist-info/METADATA
gobc_pa-1.3.dist-info/WHEEL
gobc_pa-1.3.dist-info/licenses/LICENSE
gobc_pa-1.3.dist-info/RECORD
