Metadata-Version: 2.1
Name: GOBC_PA
Version: 1.3
Summary: A new unconstrained global optimization method based on clustering and parabolic approximation
Author-email: Ihsan Pence <ihsanpence@mehmetakif.edu.tr>
License-File: LICENSE
Classifier: License :: OSI Approved :: MIT License
Classifier: Operating System :: OS Independent
Classifier: Programming Language :: Python :: 3
Requires-Python: >=3.7
